lime_trading_api/__init__.py
lime_trading_api/limeTradingApi.so
lime_trading_api/lime_ffi.py
lime_trading_api/lime_types.py
lime_trading_api-0.0.11.dist-info/LICENSE
lime_trading_api-0.0.11.dist-info/METADATA
lime_trading_api-0.0.11.dist-info/WHEEL
lime_trading_api-0.0.11.dist-info/top_level.txt
lime_trading_api-0.0.11.dist-info/RECORD
