Metadata-Version: 2.1
Name: lime-trading-api
Version: 0.0.11
Summary: Official python API wrapper for Lime Direct
Home-page: https://docs.lime.co/python
Author: Lime Financial
Author-email: support@lime.co
Keywords: Lime Financial Trading Brokerage API
License-File: LICENSE
